infrash/__init__.py
infrash/__init__.py.bak
infrash/__main__.py
infrash/cli.py
infrash/__pycache__/__init__.cpython-312.pyc
infrash/__pycache__/__init__.cpython-313.pyc
infrash/__pycache__/__main__.cpython-312.pyc
infrash/__pycache__/__main__.cpython-313.pyc
infrash/__pycache__/cli.cpython-312.pyc
infrash/__pycache__/cli.cpython-313.pyc
infrash/core/__init__.py
infrash/core/config.py
infrash/core/diagnostics.py
infrash/core/installer.py
infrash/core/runner.py
infrash/core/__pycache__/__init__.cpython-312.pyc
infrash/core/__pycache__/__init__.cpython-313.pyc
infrash/core/__pycache__/config.cpython-312.pyc
infrash/core/__pycache__/config.cpython-313.pyc
infrash/core/__pycache__/installer.cpython-312.pyc
infrash/core/__pycache__/runner.cpython-312.pyc
infrash/core/__pycache__/runner.cpython-313.pyc
infrash/core/diagnostics/__init__.py
infrash/core/diagnostics/asyncio.py
infrash/core/diagnostics/base.py
infrash/core/diagnostics/configuration.py
infrash/core/diagnostics/connection.py
infrash/core/diagnostics/database.py
infrash/core/diagnostics/dependencies.py
infrash/core/diagnostics/filesystem.py
infrash/core/diagnostics/hardware.py
infrash/core/diagnostics/logs.py
infrash/core/diagnostics/networking.py
infrash/core/diagnostics/process.py
infrash/core/diagnostics/repository.py
infrash/core/diagnostics/resources.py
infrash/core/diagnostics/script.py
infrash/core/diagnostics/__pycache__/__init__.cpython-312.pyc
infrash/core/diagnostics/__pycache__/__init__.cpython-313.pyc
infrash/core/diagnostics/__pycache__/asyncio.cpython-312.pyc
infrash/core/diagnostics/__pycache__/asyncio.cpython-313.pyc
infrash/core/diagnostics/__pycache__/base.cpython-312.pyc
infrash/core/diagnostics/__pycache__/base.cpython-313.pyc
infrash/core/diagnostics/__pycache__/configuration.cpython-312.pyc
infrash/core/diagnostics/__pycache__/configuration.cpython-313.pyc
infrash/core/diagnostics/__pycache__/connection.cpython-312.pyc
infrash/core/diagnostics/__pycache__/connection.cpython-313.pyc
infrash-0.1.9.dist-info/licenses/LICENSE
infrash-0.1.9.dist-info/METADATA
infrash-0.1.9.dist-info/WHEEL
infrash-0.1.9.dist-info/entry_points.txt
infrash-0.1.9.dist-info/top_level.txt
infrash-0.1.9.dist-info/RECORD
