Metadata-Version: 2.4
Name: infrash
Version: 0.1.9
Summary: Inteligentny runner do rozwiązywania problemów infrastrukturalnych
Home-page: https://infrash.infrash.com
Author: Tom Sapletta
Author-email: Twoje Imię <twoj.email@example.com>
License: MIT
Project-URL: Homepage, https://github.com/username/infrash
Project-URL: Bug Tracker, https://github.com/username/infrash/issues
Keywords: infrastructure,deployment,automation,diagnostics,devops
Classifier: Development Status :: 4 - Beta
Classifier: License :: OSI Approved :: Apache Software License
Classifier: Programming Language :: Python
Classifier: Programming Language :: Python :: 3
Classifier: Programming Language :: Python :: 3.8
Classifier: Programming Language :: Python :: 3.9
Classifier: Programming Language :: Python :: 3.10
Classifier: Programming Language :: Python :: 3.11
Classifier: Topic :: Software Development :: Libraries :: Python Modules
Classifier: Topic :: System :: Installation/Setup
Classifier: Topic :: System :: Systems Administration
Requires-Python: >=3.8
License-File: LICENSE
Requires-Dist: click>=8.0.0
Requires-Dist: GitPython>=3.1.0
Requires-Dist: requests>=2.25.0
Requires-Dist: rich>=10.0.0
Requires-Dist: pyyaml>=6.0
Requires-Dist: psutil>=5.9.0
Requires-Dist: packaging>=21.0
Dynamic: license-file
